zq_auth_sdk/__init__.py
zq_auth_sdk/client/__init__.py
zq_auth_sdk/client/api/__init__.py
zq_auth_sdk/client/api/app.py
zq_auth_sdk/client/api/base.py
zq_auth_sdk/client/base.py
zq_auth_sdk/entities/__init__.py
zq_auth_sdk/entities/response.py
zq_auth_sdk/entities/types.py
zq_auth_sdk/exceptions.py
zq_auth_sdk/storage/__init__.py
zq_auth_sdk/storage/memcachedstorage.py
zq_auth_sdk/storage/memorystorage.py
zq_auth_sdk/storage/redisstorage.py
zq_auth_sdk/utils.py
zq_auth_sdk-0.1.0.dist-info/LICENSE
zq_auth_sdk-0.1.0.dist-info/METADATA
zq_auth_sdk-0.1.0.dist-info/WHEEL
zq_auth_sdk-0.1.0.dist-info/RECORD
