Metadata-Version: 2.1
Name: zq-auth-sdk
Version: 0.1.0
Summary: 自强统一认证 Python SDK
Home-page: https://github.com/ZiqiangStudio/zq_auth_sdk_python
License: MIT
Keywords: Ziqiang Studio,sso,Python SDK
Author: Nagico
Author-email: yjr888@vip.qq.com
Requires-Python: >=3.8.1,<4.0
Classifier: License :: OSI Approved :: MIT License
Classifier: Programming Language :: Python
Classifier: Programming Language :: Python :: 3
Classifier: Programming Language :: Python :: 3.9
Classifier: Programming Language :: Python :: 3.10
Classifier: Programming Language :: Python :: 3.11
Classifier: Programming Language :: Python :: 3.10
Classifier: Programming Language :: Python :: 3.11
Classifier: Programming Language :: Python :: 3.9
Classifier: Topic :: Software Development :: Libraries
Classifier: Topic :: Software Development :: Libraries :: Python Modules
Classifier: Topic :: Utilities
Requires-Dist: requests (>=2.4.3)
Project-URL: Documentation, https://docs.auth.ziqiang.net.cn
Project-URL: Repository, https://github.com/ZiqiangStudio/zq_auth_sdk_python.git
Project-URL: issues, https://github.com/ZiqiangStudio/zq_auth_sdk_python/issues
